LICENSE
MANIFEST.in
README.md
setup.py
bin/htq
htq/__init__.py
htq/api.py
htq/db.py
htq/service.py
htq/utils.py
htq.egg-info/PKG-INFO
htq.egg-info/SOURCES.txt
htq.egg-info/dependency_links.txt
htq.egg-info/requires.txt
htq.egg-info/top_level.txt