Metadata-Version: 1.1
Name: htq
Version: 0.1.0
Summary: HTTP Task Queue
Home-page: https://github.com/cbmi/htq/
Author: Byron Ruth
Author-email: b@devel.io
License: BSD
Keywords: http task queue
Platform: UNKNOWN
Classifier: Development Status :: 3 - Alpha
Classifier: License :: OSI Approved :: BSD License
Classifier: Intended Audience :: Developers
Classifier: Intended Audience :: Science/Research
Classifier: Programming Language :: Python :: 3.3
Classifier: Programming Language :: Python :: 3.4
